pykegg/KGML_graph.py
pykegg/__init__.py
pykegg/utils.py
pykegg-0.1.7.dist-info/METADATA
pykegg-0.1.7.dist-info/WHEEL
pykegg-0.1.7.dist-info/licenses/LICENSE
pykegg-0.1.7.dist-info/RECORD
