Metadata-Version: 2.3
Name: pykegg
Version: 0.1.7
Summary: Visualizing and analyzing KEGG information in Python
Project-URL: Homepage, https://github.com/noriakis/pykegg
Project-URL: Bug Tracker, https://github.com/noriakis/pykegg/issues
Author-email: Noriaki Sato <nori@hgc.jp>
License-File: LICENSE
Classifier: License :: OSI Approved :: MIT License
Classifier: Operating System :: OS Independent
Classifier: Programming Language :: Python :: 3
Requires-Python: >=3.7
Requires-Dist: biopython
Requires-Dist: igraph
Requires-Dist: matplotlib
Requires-Dist: opencv-python
Requires-Dist: pandas
Requires-Dist: requests
